tina_mgr/__init__.py
tina_mgr/db.py
tina_mgr/defs.py
tina_mgr/parse.py
tina_mgr/convert/__init__.py
tina_mgr/convert/__main__.py
tina_mgr/convert/formats/__init__.py
tina_mgr/convert/formats/f_base.py
tina_mgr/convert/formats/f_json.py
tina_mgr/convert/formats/f_tina.py
tina_mgr/convert/formats/f_yaml.py
tina_mgr-0.1.14.dist-info/METADATA
tina_mgr-0.1.14.dist-info/WHEEL
tina_mgr-0.1.14.dist-info/entry_points.txt
tina_mgr-0.1.14.dist-info/licenses/LICENSES/GPL-2.0-or-later.txt
tina_mgr-0.1.14.dist-info/RECORD
