Metadata-Version: 2.4
Name: tina-mgr
Version: 0.1.14
Summary: Handle the database files of the Tina personal information manager
Project-URL: Homepage, https://devel.ringlet.net/misc/tina/
Project-URL: Changes, https://devel.ringlet.net/misc/tina/changes/
Project-URL: Issue Tracker, https://gitlab.com/tina-mgr/tina-mgr/-/issues
Project-URL: Source Code, https://gitlab.com/tina-mgr/tina-mgr
Author-email: Peter Pentchev <roam@ringlet.net>
License-Expression: GPL-2.0-or-later
License-File: LICENSES/GPL-2.0-or-later.txt
Classifier: Development Status :: 2 - Pre-Alpha
Classifier: Environment :: Console
Classifier: Intended Audience :: Developers
Classifier: Intended Audience :: End Users/Desktop
Classifier: Operating System :: POSIX
Classifier: Programming Language :: Python
Classifier: Programming Language :: Python :: 3
Classifier: Programming Language :: Python :: 3 :: Only
Classifier: Programming Language :: Python :: 3.11
Classifier: Programming Language :: Python :: 3.12
Classifier: Programming Language :: Python :: 3.13
Classifier: Programming Language :: Python :: 3.14
Classifier: Topic :: File Formats
Classifier: Topic :: Software Development :: Libraries
Classifier: Topic :: Software Development :: Libraries :: Python Modules
Classifier: Topic :: Software Development :: Testing
Classifier: Topic :: Software Development :: Testing :: Unit
Classifier: Topic :: Utilities
Classifier: Typing :: Typed
Requires-Python: >=3.11
Requires-Dist: click<9,>=8.1.3
Requires-Dist: pyparsing<4,>=3.0.9
Requires-Dist: pyyaml<7,>=6
